README.txt
setup.cfg
setup.py
ckanrdf/__init__.py
ckanrdf/ckanlinks.py
ckanrdf/command.py
ckanrdf/corscheck.py
ckanrdf/namespace.py
ckanrdf/package.py
ckanrdf.egg-info/PKG-INFO
ckanrdf.egg-info/SOURCES.txt
ckanrdf.egg-info/dependency_links.txt
ckanrdf.egg-info/entry_points.txt
ckanrdf.egg-info/not-zip-safe
ckanrdf.egg-info/paste_deploy_config.ini_tmpl
ckanrdf.egg-info/requires.txt
ckanrdf.egg-info/top_level.txt