Metadata-Version: 1.0
Name: ckanrdf
Version: 0.6.2
Summary: CKAN Catalogue RDF Generation
Home-page: UNKNOWN
Author: William Waites
Author-email: ww@styx.org
License: GPL
Keywords: ckan rdf data catalogue
Platform: UNKNOWN
